Metadata-Version: 2.1
Name: blender-stubs
Version: 3.12.27
Summary: API stubs for Blender and UPBGE generated with bpystubgen.
Home-page: https://github.com/mysticfall/bpystubgen
Author: Xavier Cho
Author-email: mysticfallband@gmail.com
License: UNKNOWN
Platform: UNKNOWN
Classifier: Programming Language :: Python :: 3
Classifier: License :: OSI Approved :: GNU General Public License v3 or later (GPLv3+)
Classifier: Operating System :: OS Independent
Classifier: Topic :: Multimedia :: Graphics :: 3D Modeling
Classifier: Topic :: Multimedia :: Graphics :: 3D Rendering
Classifier: Topic :: Text Editors :: Integrated Development Environments (IDE)
